remora/__init__.py
remora/activations.py
remora/constants.py
remora/data_chunks.py
remora/data_chunks_core.cpython-311-darwin.so
remora/data_chunks_core.pyx
remora/download.py
remora/duplex_utils.py
remora/encoded_kmers.cpython-311-darwin.so
remora/encoded_kmers.pyx
remora/inference.py
remora/io.py
remora/log.py
remora/main.py
remora/metrics.py
remora/model_util.py
remora/parsers.py
remora/prepare_train_data.py
remora/refine_signal_map.py
remora/refine_signal_map_core.cpython-311-darwin.so
remora/refine_signal_map_core.pyx
remora/train_model.py
remora/util.py
remora/validate.py
remora/trained_models/readme.rst
ont_remora-3.2.0.dist-info/LICENSE.txt
ont_remora-3.2.0.dist-info/METADATA
ont_remora-3.2.0.dist-info/WHEEL
ont_remora-3.2.0.dist-info/entry_points.txt
ont_remora-3.2.0.dist-info/top_level.txt
ont_remora-3.2.0.dist-info/RECORD
