Metadata-Version: 2.1
Name: ont-remora
Version: 3.2.0
Summary: Nanopore methylation/modified base calling detached from basecalling
Home-page: https://github.com/nanoporetech/remora
License: ont_public_licence
Platform: any
Classifier: Development Status :: 4 - Beta
Classifier: Programming Language :: Python
License-File: LICENSE.txt
Requires-Dist: tqdm
Requires-Dist: toml
Requires-Dist: torch
Requires-Dist: numpy
Requires-Dist: scikit-learn
Requires-Dist: thop
Requires-Dist: pod5 >=0.2.8
Requires-Dist: pysam >=0.20.0
Requires-Dist: parasail
Requires-Dist: requests
Requires-Dist: polars
Requires-Dist: plotnine ==0.12.4
Requires-Dist: importlib-resources
Provides-Extra: tests
Requires-Dist: pytest ; extra == 'tests'
Requires-Dist: pytest-cov ; extra == 'tests'
Requires-Dist: black ==22.8.0 ; extra == 'tests'
Requires-Dist: flake8 ; extra == 'tests'
Requires-Dist: sphinx ; extra == 'tests'
Requires-Dist: build ; extra == 'tests'
Requires-Dist: jupyter ; extra == 'tests'
Requires-Dist: patchworklib ==0.6.3 ; extra == 'tests'
Requires-Dist: scipy ; extra == 'tests'
